kinpfn/__init__.py
kinpfn/bar_distribution.py
kinpfn/decoders.py
kinpfn/encoders.py
kinpfn/initializers.py
kinpfn/layer.py
kinpfn/model.py
kinpfn/pfn_bo_bayesmark.py
kinpfn/positional_encodings.py
kinpfn/prior_kinpfn.py
kinpfn/train.py
kinpfn/train_kinpfn.py
kinpfn/transformer.py
kinpfn/utils.py
kinpfn/priors/__init__.py
kinpfn/priors/condition_on_area_of_opt_continuous.py
kinpfn/priors/gp.py
kinpfn/priors/input_warping.py
kinpfn/priors/prior.py
kinpfn/priors/prior_bag.py
kinpfn/priors/utils.py
kinpfn-1.2.1.dist-info/LICENSE
kinpfn-1.2.1.dist-info/METADATA
kinpfn-1.2.1.dist-info/WHEEL
kinpfn-1.2.1.dist-info/top_level.txt
kinpfn-1.2.1.dist-info/RECORD
