Metadata-Version: 2.2
Name: kinpfn
Version: 1.2.1
Summary: A package for KinPFN, a novel prior-data fitted network (PFN) for the approximation of kinetic RNA folding time distributions.
Author-email: Dominik Scheuer <dom.scheuer@gmail.com>, Frederic Runge <runget@cs.uni-freiburg.de>
License:                                  Apache License
Project-URL: Homepage, https://github.com/automl/KinPFN
Project-URL: Issues, https://github.com/automl/KinPFN/issues
Classifier: Programming Language :: Python
Classifier: Programming Language :: Python :: 3
Classifier: Programming Language :: Python :: 3.9
Classifier: Programming Language :: Python :: 3.10
Classifier: Programming Language :: Python :: 3.11
Classifier: License :: OSI Approved :: Apache Software License
Classifier: Intended Audience :: Science/Research
Classifier: Topic :: Scientific/Engineering
Classifier: Operating System :: OS Independent
Requires-Python: >=3.9
License-File: LICENSE
Requires-Dist: numpy==1.26.4
Requires-Dist: torch==2.4.1
Requires-Dist: scipy==1.13.1
Requires-Dist: matplotlib==3.9.2
Requires-Dist: pandas==2.2.2
Requires-Dist: polars==1.6.0
Requires-Dist: scikit-learn==1.5.1
Requires-Dist: tqdm
